_amplpy_xpress_swig.cpython-37m-x86_64-linux-gnu.so
amplpy_xpress/.gitignore
amplpy_xpress/patch.py
amplpy_xpress/__init__.py
amplpy_xpress/cpp/ampls/CMakeLists.txt
amplpy_xpress/cpp/ampls/src/csvReader.h
amplpy_xpress/cpp/ampls/src/ampls.cpp
amplpy_xpress/cpp/ampls/src/csvReader.cpp
amplpy_xpress/cpp/ampls/include/ampls/ampls.h
amplpy_xpress/cpp/ampls/examples/loadModel.cpp
amplpy_xpress/cpp/ampls/examples/callbacks.cpp
amplpy_xpress/cpp/ampls/examples/benders.cpp
amplpy_xpress/cpp/ampls/examples/tsp.cpp
amplpy_xpress/cpp/ampls/examples/addEntities.cpp
amplpy_xpress/cpp/ampls/examples/getInformation.cpp
amplpy_xpress/cpp/ampls/examples/multipleSolutions.cpp
amplpy_xpress/cpp/ampls/examples/multipleModels.cpp
amplpy_xpress/cpp/ampls/examples/errorDetection.cpp
amplpy_xpress/cpp/ampls/examples/setOptions.cpp
amplpy_xpress/cpp/ampls/examples/cuttingStock.cpp
amplpy_xpress/cpp/ampls/examples/stoppingCriteria.cpp
amplpy_xpress/cpp/ampls/test/addEntities-test.cpp
amplpy_xpress/cpp/ampls/test/tsp-test.cpp
amplpy_xpress/cpp/ampls/test/multipleModels-test.cpp
amplpy_xpress/cpp/ampls/test/loadModel-test.cpp
amplpy_xpress/cpp/ampls/test/test-execute.h
amplpy_xpress/cpp/ampls/test/setOptions-test.cpp
amplpy_xpress/cpp/ampls/test/getInformation-test.cpp
amplpy_xpress/cpp/ampls/test/test-base.h
amplpy_xpress/cpp/ampls/test/errorDetection-test.cpp
amplpy_xpress/cpp/ampls/test/multipleSolutions-test.cpp
amplpy_xpress/cpp/ampls/test/cuttingStock-test.cpp
amplpy_xpress/cpp/ampls/swig/ampls-common.i
amplpy_xpress/cpp/xpress/src/xpress_callback.cpp
amplpy_xpress/cpp/xpress/src/xpress_interface.cpp
amplpy_xpress/cpp/xpress/include/xpress_callback.h
amplpy_xpress/cpp/xpress/include/xpress_interface.h
amplpy_xpress/cpp/xpress/test/xpress-test.cpp
amplpy_xpress/cpp/xpress/swig/xpress-common.i
amplpy_xpress/tests/test_cuttingstock.py
amplpy_xpress/tests/test_multiple_solutions.py
amplpy_xpress/tests/test_tsp.py
amplpy_xpress/tests/test_base.py
amplpy_xpress-0.2.1.dist-info/WHEEL
amplpy_xpress-0.2.1.dist-info/top_level.txt
amplpy_xpress-0.2.1.dist-info/RECORD
amplpy_xpress-0.2.1.dist-info/METADATA
